{
  "db_name": "SQLite",
  "query": "\n        SELECT id, description, done\n        FROM todos\n        ORDER BY id\n                ",
  "describe": {
    "columns": [
      {
        "name": "id",
        "ordinal": 0,
        "type_info": "Integer"
      },
      {
        "name": "description",
        "ordinal": 1,
        "type_info": "Text"
      },
      {
        "name": "done",
        "ordinal": 2,
        "type_info": "Bool"
      }
    ],
    "parameters": {
      "Right": 0
    },
    "nullable": [
      false,
      false,
      false
    ]
  },
  "hash": "f55d0b3dfd39b133bb74e318620bc35e0add485bce3fb1e2ad41b07495872d4a"
}
